vlamalib/__init__.py
vlamalib/hello.py
vlamalib-0.0.2.dist-info/LICENSE.txt
vlamalib-0.0.2.dist-info/METADATA
vlamalib-0.0.2.dist-info/WHEEL
vlamalib-0.0.2.dist-info/top_level.txt
vlamalib-0.0.2.dist-info/RECORD
